pyMissingAHP/__init__.py
pyMissingAHP/algorithm/__init__.py
pyMissingAHP/algorithm/src.py
pyMissingAHP/util/__init__.py
pyMissingAHP/util/ahp.py
pyMissingAHP/util/fuzzy_ahp.py
pyMissingAHP/util/ga.py
pyMissingAHP/util/u_n_iii.py
pyMissingAHP-1.1.7.dist-info/LICENSE
pyMissingAHP-1.1.7.dist-info/METADATA
pyMissingAHP-1.1.7.dist-info/WHEEL
pyMissingAHP-1.1.7.dist-info/top_level.txt
pyMissingAHP-1.1.7.dist-info/zip-safe
pyMissingAHP-1.1.7.dist-info/RECORD
