Metadata-Version: 2.1
Name: pyMissingAHP
Version: 1.1.7
Summary: A Method to Infer AHP Missing Pairwise Comparisons
Home-page: https://github.com/Valdecy/pyMissingAHP
Author: Valdecy Pereira
Author-email: valdecy.pereira@gmail.com
License: GNU
License-File: LICENSE
Requires-Dist: numpy
Requires-Dist: pandas
Requires-Dist: plotly
Requires-Dist: matplotlib
Requires-Dist: scipy
